tunnelify/__init__.py
tunnelify/binary_manager.py
tunnelify/core.py
tunnelify-0.4.0.dist-info/METADATA
tunnelify-0.4.0.dist-info/WHEEL
tunnelify-0.4.0.dist-info/top_level.txt
tunnelify-0.4.0.dist-info/RECORD
