Metadata-Version: 2.4
Name: tunnelify
Version: 0.4.0
Summary: A simple package for easily creating Cloudflare or Localtunnel tunnels.
Author-email: Yusuf YILDIRIM <yusuf@tachion.tech>
License: MIT
Project-URL: Homepage, https://github.com/MYusufY/tunnelify
Classifier: Programming Language :: Python :: 3
Classifier: Operating System :: OS Independent
Classifier: License :: OSI Approved :: MIT License
Classifier: Topic :: Internet :: Proxy Servers
Classifier: Topic :: System :: Networking
Requires-Python: >=3.6
Requires-Dist: requests>=2.25.0
